[
  {"ffmax_guild_id":"60740304","guild_name":"Hawk Eye 01","roles":[{"role_id":"1146398643390263509","name":"Hawk Eye ⭐"},{"role_id":"1146811896335454309","name":"1"}]},
  {"ffmax_guild_id":"61131109","guild_name":"Hawk Eye 02","roles":[{"role_id":"1146398643390263509","name":"Hawk Eye ⭐"},{"role_id":"1146811902136168489","name":"2"}]},
  {"ffmax_guild_id":"61639952","guild_name":"Hawk Eye 03","roles":[{"role_id":"1146398643390263509","name":"Hawk Eye ⭐"},{"role_id":"1146811919525744750","name":"3"}]},
  {"ffmax_guild_id":"60618087","guild_name":"Hawk Eye 04","roles":[{"role_id":"1146398643390263509","name":"Hawk Eye ⭐"},{"role_id":"1146811913796341800","name":"4"}]},
  {"ffmax_guild_id":"60993239","guild_name":"Hawk Eye 05","roles":[{"role_id":"1146398643390263509","name":"Hawk Eye ⭐"},{"role_id":"1146811916073840721","name":"5"}]},
  {"ffmax_guild_id":"62467926","guild_name":"Hawk Eye 06","roles":[{"role_id":"1146398643390263509","name":"Hawk Eye ⭐"},{"role_id":"1146811928971317329","name":"6"}]},
  {"ffmax_guild_id":"63299215","guild_name":"Hawk Eye 07","roles":[{"role_id":"1146398643390263509","name":"Hawk Eye ⭐"},{"role_id":"1146811948151873536","name":"7"}]},
  {"ffmax_guild_id":"62009747","guild_name":"Hawk Eye 08","roles":[{"role_id":"1146398643390263509","name":"Hawk Eye ⭐"},{"role_id":"1146811926630907954","name":"8"}]},
  {"ffmax_guild_id":"63582136","guild_name":"Hawk Eye 09","roles":[{"role_id":"1146398643390263509","name":"Hawk Eye ⭐"},{"role_id":"1146811938412711978","name":"9"}]},
  {"ffmax_guild_id":"64108372","guild_name":"Hawk Eye 10","roles":[{"role_id":"1146398643390263509","name":"Hawk Eye ⭐"},{"role_id":"1146811931387232367","name":"10"}]},
  {"ffmax_guild_id":"65089147","guild_name":"Hawk Eye X1","roles":[{"role_id":"1146398643390263509","name":"Hawk Eye ⭐"},{"role_id":"1146811933597651015","name":"X1"}]},
  {"ffmax_guild_id":"111","guild_name":"Hawk Eye X2","roles":[{"role_id":"1146398643390263509","name":"Hawk Eye ⭐"},{"role_id":"1146811936227475627","name":"X2 (Removed)"}]},
  {"ffmax_guild_id":"3009325153","guild_name":"Hawk Eye X3","roles":[{"role_id":"1146398643390263509","name":"Hawk Eye ⭐"},{"role_id":"1285639948678205654","name":"X3"}]},
  {"ffmax_guild_id":"61369463","guild_name":"Hawk Eye X4","roles":[{"role_id":"1146398643390263509","name":"Hawk Eye ⭐"},{"role_id":"1296021438230167552","name":"X4"}]},
  {"ffmax_guild_id":"62439929","guild_name":"Hawk Eye X5","roles":[{"role_id":"1146398643390263509","name":"Hawk Eye ⭐"},{"role_id":"1146811950509068288","name":"X5"}]},
  {"ffmax_guild_id":"3008075139","guild_name":"Hawk Eye X6","roles":[{"role_id":"1146398643390263509","name":"Hawk Eye ⭐"},{"role_id":"1310181473634226206","name":"X6"}]},
  {"ffmax_guild_id":"3014128530","guild_name":"Hawk Eye X7","roles":[{"role_id":"1146398643390263509","name":"Hawk Eye ⭐"},{"role_id":"1333757034205810708","name":"X7"}]}
]